{"assets/fonts/Roboto-Regular.ttf":["assets/fonts/Roboto-Regular.ttf"],"assets/icons/Smile.svg":["assets/icons/Smile.svg"],"assets/icons/alert_gray_rounded.svg":["assets/icons/alert_gray_rounded.svg"],"assets/icons/before_smile.svg":["assets/icons/before_smile.svg"],"assets/icons/blue_plus.svg":["assets/icons/blue_plus.svg"],"assets/icons/plus.svg":["assets/icons/plus.svg"],"assets/images/ad1.png":["assets/images/ad1.png"],"assets/test_icon/main_icon_1.png":["assets/test_icon/main_icon_1.png"],"assets/test_icon/main_icon_2.png":["assets/test_icon/main_icon_2.png"],"assets/test_icon/main_icon_3.png":["assets/test_icon/main_icon_3.png"],"assets/test_icon/main_icon_4.png":["assets/test_icon/main_icon_4.png"],"assets/test_icon/main_icon_5.png":["assets/test_icon/main_icon_5.png"],"packages/cupertino_icons/assets/CupertinoIcons.ttf":["packages/cupertino_icons/assets/CupertinoIcons.ttf"],"packages/flutter_inappwebview/assets/t_rex_runner/t-rex.css":["packages/flutter_inappwebview/assets/t_rex_runner/t-rex.css"],"packages/flutter_inappwebview/assets/t_rex_runner/t-rex.html":["packages/flutter_inappwebview/assets/t_rex_runner/t-rex.html"]}